scopinator/README.md
scopinator/__init__.py
scopinator/__version__.py
scopinator/cli/__init__.py
scopinator/cli/commands/__init__.py
scopinator/cli/commands/discovery.py
scopinator/cli/commands/profile.py
scopinator/cli/connection_state.py
scopinator/cli/interactive.py
scopinator/cli/interactive_simple.py
scopinator/cli/main.py
scopinator/cli/protocol_helper.py
scopinator/cli/repl_enhanced.py
scopinator/imaging/fits_handler.py
scopinator/imaging/graxpert_stretch.py
scopinator/imaging/image_processor.py
scopinator/imaging/stretch.py
scopinator/imaging/upscaler.py
scopinator/profile/__init__.py
scopinator/profile/astronomy_profile.py
scopinator/profile/components/__init__.py
scopinator/profile/components/base.py
scopinator/py.typed
scopinator/seestar/__init__.py
scopinator/seestar/client.py
scopinator/seestar/commands/__init__.py
scopinator/seestar/commands/common.py
scopinator/seestar/commands/discovery.py
scopinator/seestar/commands/imaging.py
scopinator/seestar/commands/parameterized.py
scopinator/seestar/commands/planner.py
scopinator/seestar/commands/responses.py
scopinator/seestar/commands/settings.py
scopinator/seestar/commands/simple.py
scopinator/seestar/connection.py
scopinator/seestar/events/__init__.py
scopinator/seestar/imaging_client.py
scopinator/seestar/plans/__init__.py
scopinator/seestar/protocol_handlers.py
scopinator/seestar/rtspclient.py
scopinator/sequencer/README.md
scopinator/sequencer/__init__.py
scopinator/sequencer/base.py
scopinator/sequencer/commands.py
scopinator/sequencer/events.py
scopinator/sequencer/examples.py
scopinator/sequencer/sequence.py
scopinator/util/__init__.py
scopinator/util/asyncproxy.py
scopinator/util/asyncutil.py
scopinator/util/connection.py
scopinator/util/eventbus.py
scopinator/util/logging_config.py
scopinator/v2/__init__.py
scopinator/v2/backends/__init__.py
scopinator/v2/backends/alpaca/__init__.py
scopinator/v2/backends/alpaca/backend.py
scopinator/v2/backends/alpaca/camera.py
scopinator-2025.12.2.dist-info/WHEEL
scopinator-2025.12.2.dist-info/entry_points.txt
scopinator-2025.12.2.dist-info/METADATA
scopinator-2025.12.2.dist-info/RECORD
