Metadata-Version: 2.4
Name: scopinator
Version: 2025.12.2
Summary: A library for controlling telescopes (initially Seestars)
Author: Steven
Author-email: Steven <erewhon@flatland.org>
License-Expression: GPL-3.0-or-later
Classifier: Programming Language :: Python :: 3
Classifier: Operating System :: OS Independent
Requires-Dist: click>=8.1.0,<8.2
Requires-Dist: click-repl>=0.3.0
Requires-Dist: click-completion>=0.5.2
Requires-Dist: pydantic>=2.0.0
Requires-Dist: loguru
Requires-Dist: beartype
Requires-Dist: pydash
Requires-Dist: tzlocal
Requires-Dist: numpy
Requires-Dist: numpy-typing>=1.1.1
Requires-Dist: opencv-python
Requires-Dist: psutil>=5.9.8
Requires-Dist: pillow
Requires-Dist: aiohttp>=3.8.0
Requires-Dist: pyyaml>=6.0
Requires-Dist: pyindi-client>=2.0.0 ; extra == 'indi'
Requires-Python: >=3.12
Project-URL: Homepage, https://github.com/astrophotograph/pyscopinator
Provides-Extra: indi
